k2000/__init__.py
k2000/client.py
k2000/definitions.py
k2000/encoding.py
k2000/image.py
k2000/messages.py
k2000/utils.py
k2000-0.1.2.dist-info/LICENSE
k2000-0.1.2.dist-info/METADATA
k2000-0.1.2.dist-info/WHEEL
k2000-0.1.2.dist-info/top_level.txt
k2000-0.1.2.dist-info/RECORD
